{
 "cells": [
  {
   "cell_type": "code",
   "execution_count": 7,
   "metadata": {},
   "outputs": [],
   "source": [
    "import numpy as np\n",
    "import math\n",
    "import ast"
   ]
  },
  {
   "cell_type": "code",
   "execution_count": 8,
   "metadata": {},
   "outputs": [],
   "source": [
    "f = open(\"input.txt\", \"r\")\n",
    "rawstring = f.read()\n",
    "f.close()"
   ]
  },
  {
   "cell_type": "code",
   "execution_count": 9,
   "metadata": {},
   "outputs": [],
   "source": [
    "bytes = bytearray.fromhex(rawstring)\n",
    "bytes_as_bits = ''.join(format(byte, '08b') for byte in bytes)\n"
   ]
  },
  {
   "cell_type": "code",
   "execution_count": 10,
   "metadata": {},
   "outputs": [],
   "source": [
    "literals = []\n",
    "\n",
    "class Packet:\n",
    "    def __init__(self, version, type_id,src_string) -> None:\n",
    "        self.version = version\n",
    "        self.type_id = type_id\n",
    "        self.operator = self.type_id != 4\n",
    "        self.src_string = src_string\n",
    "        self.startSub = []\n",
    "        self.sub = []\n",
    "\n",
    "        if self.operator:\n",
    "            self.l_type_id = int(src_string[6])\n",
    "\n",
    "            if self.l_type_id == 0:\n",
    "                self.sub_length = int(src_string[7:7+15], base=2)\n",
    "                self.startSub.append(7+15)\n",
    "                self.end = 7+15+self.sub_length\n",
    "                while self.startSub[-1] != self.end:\n",
    "                    self.parseSub(self.src_string[self.startSub[-1]:self.end])\n",
    "                    self.startSub.append(self.startSub[-1]+self.sub[-1].end)\n",
    "            else: \n",
    "                self.n_sub = int(src_string[7:7+11], base=2)\n",
    "                self.startSub.append(7+11)\n",
    "                while len(self.sub) != self.n_sub:\n",
    "                    self.parseSub(self.src_string[self.startSub[-1]:])\n",
    "                    self.startSub.append(self.startSub[-1]+self.sub[-1].end)\n",
    "                self.end = self.startSub[-1]\n",
    "            \n",
    "        else:\n",
    "            #literal\n",
    "            temp = list(self.src_string[6:])\n",
    "            self.len_lit = 5\n",
    "            i=0\n",
    "            while(temp[i] != '0'):\n",
    "                self.len_lit += 5\n",
    "                temp.pop(i)\n",
    "                i += 4\n",
    "            temp.pop(i)\n",
    "            temp = temp[:i+4]\n",
    "            self.literalVal = int(\"\".join(temp),base=2)\n",
    "            self.end = 6+self.len_lit\n",
    "            self.val = self.literalVal\n",
    "            literals.append((f'l{len(literals)}',self.val))\n",
    "\n",
    "        if self.type_id == 0:\n",
    "            self.val = sum([x.val for x in self.sub])\n",
    "            self.ast = ast.Call(func=ast.Name(id='sum', ctx=ast.Load()), args=[ast.List(elts=[x.ast for x in self.sub], ctx=ast.Load())], keywords=[])\n",
    "\n",
    "        elif self.type_id == 1:\n",
    "            self.val = np.product([x.val for x in self.sub])\n",
    "            self.ast = ast.Call(func=ast.Attribute(value=ast.Name(id='math', ctx=ast.Load()), attr='prod', ctx=ast.Load()), args=[ast.List(elts=[x.ast for x in self.sub], ctx=ast.Load())], keywords=[])\n",
    "\n",
    "        elif self.type_id == 2:\n",
    "            self.val = min([x.val for x in self.sub])\n",
    "            self.ast = ast.Call(func=ast.Name(id='min', ctx=ast.Load()), args=[ast.List(elts=[x.ast for x in self.sub], ctx=ast.Load())], keywords=[])\n",
    "        elif self.type_id == 3:\n",
    "            self.val = max([x.val for x in self.sub])\n",
    "            self.ast = ast.Call(func=ast.Name(id='max', ctx=ast.Load()), args=[ast.List(elts=[x.ast for x in self.sub], ctx=ast.Load())], keywords=[])\n",
    "        elif self.type_id == 4:\n",
    "            self.ast = ast.Constant(value=self.val)\n",
    "        elif self.type_id == 5:\n",
    "            self.val = 1 if self.sub[0].val > self.sub[1].val else 0\n",
    "            self.ast = ast.IfExp(test=ast.Compare(left=self.sub[0].ast, ops=[ast.Gt()], comparators=[self.sub[1].ast]), body=ast.Constant(value=1), orelse=ast.Constant(value=0))\n",
    "        elif self.type_id == 6:\n",
    "            self.val = 1 if self.sub[0].val < self.sub[1].val else 0\n",
    "            self.ast = ast.IfExp(test=ast.Compare(left=self.sub[0].ast, ops=[ast.Lt()], comparators=[self.sub[1].ast]), body=ast.Constant(value=1), orelse=ast.Constant(value=0))\n",
    "        elif self.type_id == 7:\n",
    "            self.val = 1 if self.sub[0].val == self.sub[1].val else 0\n",
    "            self.ast = ast.IfExp(test=ast.Compare(left=self.sub[0].ast, ops=[ast.Eq()], comparators=[self.sub[1].ast]), body=ast.Constant(value=1), orelse=ast.Constant(value=0))\n",
    "\n",
    "        \n",
    "\n",
    "    def summedVersion(self):\n",
    "        return self.version + sum([x.summedVersion() for x in self.sub])\n",
    "\n",
    "    def parseSub(self, src_string):\n",
    "        self.sub.append(inter := Packet.fromString(src_string))\n",
    "\n",
    "    @staticmethod\n",
    "    def fromString(src_string):\n",
    "        version = int(src_string[0:3], base=2)\n",
    "        type_id = int(src_string[3:6], base=2)\n",
    "        return Packet(version, type_id, src_string)"
   ]
  },
  {
   "cell_type": "code",
   "execution_count": 11,
   "metadata": {},
   "outputs": [],
   "source": [
    "outer = Packet.fromString(bytes_as_bits)"
   ]
  },
  {
   "cell_type": "code",
   "execution_count": 15,
   "metadata": {},
   "outputs": [
    {
     "name": "stdout",
     "output_type": "stream",
     "text": [
      "sum([min([max([min([min([min([min([math.prod([max([max([max([min([math.prod([math.prod([min([min([math.prod([max([math.prod([sum([min([1736671104])])])])])])])])])])])])])])])])])])])]), 4, max([522179]), math.prod([19219, 1 if 38942 < 247596226 else 0]), sum([math.prod([7, 8, 14]), math.prod([8, 2, 12]), math.prod([4, 10, 3])]), 131, math.prod([1 if 17052 < 2979 else 0, 46058]), sum([664609]), math.prod([1 if 2159 > 2159 else 0, 580431]), math.prod([13, 200, 84, 116]), 15, math.prod([80]), math.prod([95, 1 if 2 < 16651 else 0]), math.prod([8599772, 1 if sum([10, 14, 2]) < sum([8, 9, 11]) else 0]), 14698, min([6, 176724, 17, 218]), math.prod([1 if 2951 > 61 else 0, 30979330271]), math.prod([1 if sum([5, 2, 6]) > sum([9, 12, 2]) else 0, 35056]), max([21, 8, 10464633, 21766]), math.prod([95, 161]), math.prod([1 if 28 > 28 else 0, 1176227742]), math.prod([102, 1 if sum([2, 4, 11]) > sum([10, 15, 10]) else 0]), min([246, 1554]), math.prod([1 if 1470 == 6827177 else 0, 208]), min([728, 763810927, 55700720745]), math.prod([1 if 5916415 > 2489 else 0, 289600]), math.prod([230, 92, 120, 220, 159]), math.prod([1 if sum([11, 5, 11]) == sum([15, 14, 10]) else 0, 49769]), min([1466502782]), max([1589, 214, 13]), math.prod([1 if 170605153 < 170605153 else 0, 198398]), 18956, math.prod([196905722, 1 if 112 == 112 else 0]), sum([4217206544, 48993801750, 25736, 3879782983]), math.prod([sum([2, 15, 4]), sum([4, 15, 11]), sum([7, 15, 9])]), 211, math.prod([1 if 16 > 63733 else 0, 44586]), sum([14, 1]), max([3511, 10]), max([12718799, 171629, 9, 264022477, 98]), math.prod([535767221581, 1 if sum([12, 10, 11]) < sum([11, 2, 9]) else 0]), min([391364, 3067700, 611, 2388317100, 141]), math.prod([1 if 237 < 237 else 0, 3462]), math.prod([139, 53, 151]), 7, sum([12998225, 689, 2007, 5, 826]), 547, math.prod([193, 1 if 1458 < 138 else 0]), math.prod([1 if 277997 == 12 else 0, 37675211133]), 11, math.prod([1 if 955 > 2610 else 0, 67374456587]), sum([886515, 86, 254]), 3])\n"
     ]
    }
   ],
   "source": [
    "print(ast.unparse(ast.fix_missing_locations(module)))"
   ]
  },
  {
   "cell_type": "code",
   "execution_count": 12,
   "metadata": {},
   "outputs": [
    {
     "data": {
      "text/plain": [
       "180616437720"
      ]
     },
     "execution_count": 12,
     "metadata": {},
     "output_type": "execute_result"
    }
   ],
   "source": [
    "outer.ast\n",
    "module = ast.Module(body=[ast.Expr(value=outer.ast)],type_ignores=[],lineno=1, col_offset=1)\n",
    "eval(ast.unparse(ast.fix_missing_locations(module)))"
   ]
  },
  {
   "cell_type": "code",
   "execution_count": 13,
   "metadata": {},
   "outputs": [
    {
     "data": {
      "text/plain": [
       "180616437720"
      ]
     },
     "execution_count": 13,
     "metadata": {},
     "output_type": "execute_result"
    }
   ],
   "source": [
    "outer.val"
   ]
  },
  {
   "cell_type": "code",
   "execution_count": 20,
   "metadata": {},
   "outputs": [
    {
     "name": "stdout",
     "output_type": "stream",
     "text": [
      "  1           0 LOAD_NAME                0 (sum)\n",
      "              2 LOAD_NAME                1 (min)\n",
      "              4 LOAD_NAME                2 (max)\n",
      "              6 LOAD_NAME                1 (min)\n",
      "              8 LOAD_NAME                1 (min)\n",
      "             10 LOAD_NAME                1 (min)\n",
      "             12 LOAD_NAME                1 (min)\n",
      "             14 LOAD_NAME                3 (math)\n",
      "             16 LOAD_METHOD              4 (prod)\n",
      "             18 LOAD_NAME                2 (max)\n",
      "             20 LOAD_NAME                2 (max)\n",
      "             22 LOAD_NAME                2 (max)\n",
      "             24 LOAD_NAME                1 (min)\n",
      "             26 LOAD_NAME                3 (math)\n",
      "             28 LOAD_METHOD              4 (prod)\n",
      "             30 LOAD_NAME                3 (math)\n",
      "             32 LOAD_METHOD              4 (prod)\n",
      "             34 LOAD_NAME                1 (min)\n",
      "             36 LOAD_NAME                1 (min)\n",
      "             38 LOAD_NAME                3 (math)\n",
      "             40 LOAD_METHOD              4 (prod)\n",
      "             42 LOAD_NAME                2 (max)\n",
      "             44 LOAD_NAME                3 (math)\n",
      "             46 LOAD_METHOD              4 (prod)\n",
      "             48 LOAD_NAME                0 (sum)\n",
      "             50 LOAD_NAME                1 (min)\n",
      "             52 LOAD_CONST               0 (1736671104)\n",
      "             54 BUILD_LIST               1\n",
      "             56 CALL_FUNCTION            1\n",
      "             58 BUILD_LIST               1\n",
      "             60 CALL_FUNCTION            1\n",
      "             62 BUILD_LIST               1\n",
      "             64 CALL_METHOD              1\n",
      "             66 BUILD_LIST               1\n",
      "             68 CALL_FUNCTION            1\n",
      "             70 BUILD_LIST               1\n",
      "             72 CALL_METHOD              1\n",
      "             74 BUILD_LIST               1\n",
      "             76 CALL_FUNCTION            1\n",
      "             78 BUILD_LIST               1\n",
      "             80 CALL_FUNCTION            1\n",
      "             82 BUILD_LIST               1\n",
      "             84 CALL_METHOD              1\n",
      "             86 BUILD_LIST               1\n",
      "             88 CALL_METHOD              1\n",
      "             90 BUILD_LIST               1\n",
      "             92 CALL_FUNCTION            1\n",
      "             94 BUILD_LIST               1\n",
      "             96 CALL_FUNCTION            1\n",
      "             98 BUILD_LIST               1\n",
      "            100 CALL_FUNCTION            1\n",
      "            102 BUILD_LIST               1\n",
      "            104 CALL_FUNCTION            1\n",
      "            106 BUILD_LIST               1\n",
      "            108 CALL_METHOD              1\n",
      "            110 BUILD_LIST               1\n",
      "            112 CALL_FUNCTION            1\n",
      "            114 BUILD_LIST               1\n",
      "            116 CALL_FUNCTION            1\n",
      "            118 BUILD_LIST               1\n",
      "            120 CALL_FUNCTION            1\n",
      "            122 BUILD_LIST               1\n",
      "            124 CALL_FUNCTION            1\n",
      "            126 BUILD_LIST               1\n",
      "            128 CALL_FUNCTION            1\n",
      "            130 BUILD_LIST               1\n",
      "            132 CALL_FUNCTION            1\n",
      "            134 LOAD_CONST               1 (4)\n",
      "            136 LOAD_NAME                2 (max)\n",
      "            138 LOAD_CONST               2 (522179)\n",
      "            140 BUILD_LIST               1\n",
      "            142 CALL_FUNCTION            1\n",
      "            144 LOAD_NAME                3 (math)\n",
      "            146 LOAD_METHOD              4 (prod)\n",
      "            148 LOAD_CONST               3 (19219)\n",
      "            150 LOAD_CONST               4 (38942)\n",
      "            152 LOAD_CONST               5 (247596226)\n",
      "            154 COMPARE_OP               0 (<)\n",
      "            156 POP_JUMP_IF_FALSE      162\n",
      "            158 LOAD_CONST               6 (1)\n",
      "            160 JUMP_FORWARD             2 (to 164)\n",
      "        >>  162 LOAD_CONST               7 (0)\n",
      "        >>  164 BUILD_LIST               2\n",
      "            166 CALL_METHOD              1\n",
      "            168 LOAD_NAME                0 (sum)\n",
      "            170 LOAD_NAME                3 (math)\n",
      "            172 LOAD_METHOD              4 (prod)\n",
      "            174 BUILD_LIST               0\n",
      "            176 LOAD_CONST               8 ((7, 8, 14))\n",
      "            178 LIST_EXTEND              1\n",
      "            180 CALL_METHOD              1\n",
      "            182 LOAD_NAME                3 (math)\n",
      "            184 LOAD_METHOD              4 (prod)\n",
      "            186 BUILD_LIST               0\n",
      "            188 LOAD_CONST               9 ((8, 2, 12))\n",
      "            190 LIST_EXTEND              1\n",
      "            192 CALL_METHOD              1\n",
      "            194 LOAD_NAME                3 (math)\n",
      "            196 LOAD_METHOD              4 (prod)\n",
      "            198 BUILD_LIST               0\n",
      "            200 LOAD_CONST              10 ((4, 10, 3))\n",
      "            202 LIST_EXTEND              1\n",
      "            204 CALL_METHOD              1\n",
      "            206 BUILD_LIST               3\n",
      "            208 CALL_FUNCTION            1\n",
      "            210 LOAD_CONST              11 (131)\n",
      "            212 LOAD_NAME                3 (math)\n",
      "            214 LOAD_METHOD              4 (prod)\n",
      "            216 LOAD_CONST              12 (17052)\n",
      "            218 LOAD_CONST              13 (2979)\n",
      "            220 COMPARE_OP               0 (<)\n",
      "            222 POP_JUMP_IF_FALSE      228\n",
      "            224 LOAD_CONST               6 (1)\n",
      "            226 JUMP_FORWARD             2 (to 230)\n",
      "        >>  228 LOAD_CONST               7 (0)\n",
      "        >>  230 LOAD_CONST              14 (46058)\n",
      "            232 BUILD_LIST               2\n",
      "            234 CALL_METHOD              1\n",
      "            236 LOAD_NAME                0 (sum)\n",
      "            238 LOAD_CONST              15 (664609)\n",
      "            240 BUILD_LIST               1\n",
      "            242 CALL_FUNCTION            1\n",
      "            244 LOAD_NAME                3 (math)\n",
      "            246 LOAD_METHOD              4 (prod)\n",
      "            248 LOAD_CONST              16 (2159)\n",
      "            250 LOAD_CONST              16 (2159)\n",
      "            252 COMPARE_OP               4 (>)\n",
      "            254 EXTENDED_ARG             1\n",
      "            256 POP_JUMP_IF_FALSE      262\n",
      "            258 LOAD_CONST               6 (1)\n",
      "            260 JUMP_FORWARD             2 (to 264)\n",
      "        >>  262 LOAD_CONST               7 (0)\n",
      "        >>  264 LOAD_CONST              17 (580431)\n",
      "            266 BUILD_LIST               2\n",
      "            268 CALL_METHOD              1\n",
      "            270 LOAD_NAME                3 (math)\n",
      "            272 LOAD_METHOD              4 (prod)\n",
      "            274 BUILD_LIST               0\n",
      "            276 LOAD_CONST              18 ((13, 200, 84, 116))\n",
      "            278 LIST_EXTEND              1\n",
      "            280 CALL_METHOD              1\n",
      "            282 LOAD_CONST              19 (15)\n",
      "            284 LOAD_NAME                3 (math)\n",
      "            286 LOAD_METHOD              4 (prod)\n",
      "            288 LOAD_CONST              20 (80)\n",
      "            290 BUILD_LIST               1\n",
      "            292 CALL_METHOD              1\n",
      "            294 LOAD_NAME                3 (math)\n",
      "            296 LOAD_METHOD              4 (prod)\n",
      "            298 LOAD_CONST              21 (95)\n",
      "            300 LOAD_CONST              22 (2)\n",
      "            302 LOAD_CONST              23 (16651)\n",
      "            304 COMPARE_OP               0 (<)\n",
      "            306 EXTENDED_ARG             1\n",
      "            308 POP_JUMP_IF_FALSE      314\n",
      "            310 LOAD_CONST               6 (1)\n",
      "            312 JUMP_FORWARD             2 (to 316)\n",
      "        >>  314 LOAD_CONST               7 (0)\n",
      "        >>  316 BUILD_LIST               2\n",
      "            318 CALL_METHOD              1\n",
      "            320 LOAD_NAME                3 (math)\n",
      "            322 LOAD_METHOD              4 (prod)\n",
      "            324 LOAD_CONST              24 (8599772)\n",
      "            326 LOAD_NAME                0 (sum)\n",
      "            328 BUILD_LIST               0\n",
      "            330 LOAD_CONST              25 ((10, 14, 2))\n",
      "            332 LIST_EXTEND              1\n",
      "            334 CALL_FUNCTION            1\n",
      "            336 LOAD_NAME                0 (sum)\n",
      "            338 BUILD_LIST               0\n",
      "            340 LOAD_CONST              26 ((8, 9, 11))\n",
      "            342 LIST_EXTEND              1\n",
      "            344 CALL_FUNCTION            1\n",
      "            346 COMPARE_OP               0 (<)\n",
      "            348 EXTENDED_ARG             1\n",
      "            350 POP_JUMP_IF_FALSE      356\n",
      "            352 LOAD_CONST               6 (1)\n",
      "            354 JUMP_FORWARD             2 (to 358)\n",
      "        >>  356 LOAD_CONST               7 (0)\n",
      "        >>  358 BUILD_LIST               2\n",
      "            360 CALL_METHOD              1\n",
      "            362 LOAD_CONST              27 (14698)\n",
      "            364 LOAD_NAME                1 (min)\n",
      "            366 BUILD_LIST               0\n",
      "            368 LOAD_CONST              28 ((6, 176724, 17, 218))\n",
      "            370 LIST_EXTEND              1\n",
      "            372 CALL_FUNCTION            1\n",
      "            374 LOAD_NAME                3 (math)\n",
      "            376 LOAD_METHOD              4 (prod)\n",
      "            378 LOAD_CONST              29 (2951)\n",
      "            380 LOAD_CONST              30 (61)\n",
      "            382 COMPARE_OP               4 (>)\n",
      "            384 EXTENDED_ARG             1\n",
      "            386 POP_JUMP_IF_FALSE      392\n",
      "            388 LOAD_CONST               6 (1)\n",
      "            390 JUMP_FORWARD             2 (to 394)\n",
      "        >>  392 LOAD_CONST               7 (0)\n",
      "        >>  394 LOAD_CONST              31 (30979330271)\n",
      "            396 BUILD_LIST               2\n",
      "            398 CALL_METHOD              1\n",
      "            400 LOAD_NAME                3 (math)\n",
      "            402 LOAD_METHOD              4 (prod)\n",
      "            404 LOAD_NAME                0 (sum)\n",
      "            406 BUILD_LIST               0\n",
      "            408 LOAD_CONST              32 ((5, 2, 6))\n",
      "            410 LIST_EXTEND              1\n",
      "            412 CALL_FUNCTION            1\n",
      "            414 LOAD_NAME                0 (sum)\n",
      "            416 BUILD_LIST               0\n",
      "            418 LOAD_CONST              33 ((9, 12, 2))\n",
      "            420 LIST_EXTEND              1\n",
      "            422 CALL_FUNCTION            1\n",
      "            424 COMPARE_OP               4 (>)\n",
      "            426 EXTENDED_ARG             1\n",
      "            428 POP_JUMP_IF_FALSE      434\n",
      "            430 LOAD_CONST               6 (1)\n",
      "            432 JUMP_FORWARD             2 (to 436)\n",
      "        >>  434 LOAD_CONST               7 (0)\n",
      "        >>  436 LOAD_CONST              34 (35056)\n",
      "            438 BUILD_LIST               2\n",
      "            440 CALL_METHOD              1\n",
      "            442 LOAD_NAME                2 (max)\n",
      "            444 BUILD_LIST               0\n",
      "            446 LOAD_CONST              35 ((21, 8, 10464633, 21766))\n",
      "            448 LIST_EXTEND              1\n",
      "            450 CALL_FUNCTION            1\n",
      "            452 LOAD_NAME                3 (math)\n",
      "            454 LOAD_METHOD              4 (prod)\n",
      "            456 LOAD_CONST              21 (95)\n",
      "            458 LOAD_CONST              36 (161)\n",
      "            460 BUILD_LIST               2\n",
      "            462 CALL_METHOD              1\n",
      "            464 LOAD_NAME                3 (math)\n",
      "            466 LOAD_METHOD              4 (prod)\n",
      "            468 LOAD_CONST              37 (28)\n",
      "            470 LOAD_CONST              37 (28)\n",
      "            472 COMPARE_OP               4 (>)\n",
      "            474 EXTENDED_ARG             1\n",
      "            476 POP_JUMP_IF_FALSE      482\n",
      "            478 LOAD_CONST               6 (1)\n",
      "            480 JUMP_FORWARD             2 (to 484)\n",
      "        >>  482 LOAD_CONST               7 (0)\n",
      "        >>  484 LOAD_CONST              38 (1176227742)\n",
      "            486 BUILD_LIST               2\n",
      "            488 CALL_METHOD              1\n",
      "            490 LOAD_NAME                3 (math)\n",
      "            492 LOAD_METHOD              4 (prod)\n",
      "            494 LOAD_CONST              39 (102)\n",
      "            496 LOAD_NAME                0 (sum)\n",
      "            498 BUILD_LIST               0\n",
      "            500 LOAD_CONST              40 ((2, 4, 11))\n",
      "            502 LIST_EXTEND              1\n",
      "            504 CALL_FUNCTION            1\n",
      "            506 LOAD_NAME                0 (sum)\n",
      "            508 BUILD_LIST               0\n",
      "            510 LOAD_CONST              41 ((10, 15, 10))\n",
      "            512 LIST_EXTEND              1\n",
      "            514 CALL_FUNCTION            1\n",
      "            516 COMPARE_OP               4 (>)\n",
      "            518 EXTENDED_ARG             2\n",
      "            520 POP_JUMP_IF_FALSE      526\n",
      "            522 LOAD_CONST               6 (1)\n",
      "            524 JUMP_FORWARD             2 (to 528)\n",
      "        >>  526 LOAD_CONST               7 (0)\n",
      "        >>  528 BUILD_LIST               2\n",
      "            530 CALL_METHOD              1\n",
      "            532 LOAD_NAME                1 (min)\n",
      "            534 LOAD_CONST              42 (246)\n",
      "            536 LOAD_CONST              43 (1554)\n",
      "            538 BUILD_LIST               2\n",
      "            540 CALL_FUNCTION            1\n",
      "            542 LOAD_NAME                3 (math)\n",
      "            544 LOAD_METHOD              4 (prod)\n",
      "            546 LOAD_CONST              44 (1470)\n",
      "            548 LOAD_CONST              45 (6827177)\n",
      "            550 COMPARE_OP               2 (==)\n",
      "            552 EXTENDED_ARG             2\n",
      "            554 POP_JUMP_IF_FALSE      560\n",
      "            556 LOAD_CONST               6 (1)\n",
      "            558 JUMP_FORWARD             2 (to 562)\n",
      "        >>  560 LOAD_CONST               7 (0)\n",
      "        >>  562 LOAD_CONST              46 (208)\n",
      "            564 BUILD_LIST               2\n",
      "            566 CALL_METHOD              1\n",
      "            568 LOAD_NAME                1 (min)\n",
      "            570 BUILD_LIST               0\n",
      "            572 LOAD_CONST              47 ((728, 763810927, 55700720745))\n",
      "            574 LIST_EXTEND              1\n",
      "            576 CALL_FUNCTION            1\n",
      "            578 LOAD_NAME                3 (math)\n",
      "            580 LOAD_METHOD              4 (prod)\n",
      "            582 LOAD_CONST              48 (5916415)\n",
      "            584 LOAD_CONST              49 (2489)\n",
      "            586 COMPARE_OP               4 (>)\n",
      "            588 EXTENDED_ARG             2\n",
      "            590 POP_JUMP_IF_FALSE      596\n",
      "            592 LOAD_CONST               6 (1)\n",
      "            594 JUMP_FORWARD             2 (to 598)\n",
      "        >>  596 LOAD_CONST               7 (0)\n",
      "        >>  598 LOAD_CONST              50 (289600)\n",
      "            600 BUILD_LIST               2\n",
      "            602 CALL_METHOD              1\n",
      "            604 LOAD_NAME                3 (math)\n",
      "            606 LOAD_METHOD              4 (prod)\n",
      "            608 BUILD_LIST               0\n",
      "            610 LOAD_CONST              51 ((230, 92, 120, 220, 159))\n",
      "            612 LIST_EXTEND              1\n",
      "            614 CALL_METHOD              1\n",
      "            616 LOAD_NAME                3 (math)\n",
      "            618 LOAD_METHOD              4 (prod)\n",
      "            620 LOAD_NAME                0 (sum)\n",
      "            622 BUILD_LIST               0\n",
      "            624 LOAD_CONST              52 ((11, 5, 11))\n",
      "            626 LIST_EXTEND              1\n",
      "            628 CALL_FUNCTION            1\n",
      "            630 LOAD_NAME                0 (sum)\n",
      "            632 BUILD_LIST               0\n",
      "            634 LOAD_CONST              53 ((15, 14, 10))\n",
      "            636 LIST_EXTEND              1\n",
      "            638 CALL_FUNCTION            1\n",
      "            640 COMPARE_OP               2 (==)\n",
      "            642 EXTENDED_ARG             2\n",
      "            644 POP_JUMP_IF_FALSE      650\n",
      "            646 LOAD_CONST               6 (1)\n",
      "            648 JUMP_FORWARD             2 (to 652)\n",
      "        >>  650 LOAD_CONST               7 (0)\n",
      "        >>  652 LOAD_CONST              54 (49769)\n",
      "            654 BUILD_LIST               2\n",
      "            656 CALL_METHOD              1\n",
      "            658 LOAD_NAME                1 (min)\n",
      "            660 LOAD_CONST              55 (1466502782)\n",
      "            662 BUILD_LIST               1\n",
      "            664 CALL_FUNCTION            1\n",
      "            666 LOAD_NAME                2 (max)\n",
      "            668 BUILD_LIST               0\n",
      "            670 LOAD_CONST              56 ((1589, 214, 13))\n",
      "            672 LIST_EXTEND              1\n",
      "            674 CALL_FUNCTION            1\n",
      "            676 LOAD_NAME                3 (math)\n",
      "            678 LOAD_METHOD              4 (prod)\n",
      "            680 LOAD_CONST              57 (170605153)\n",
      "            682 LOAD_CONST              57 (170605153)\n",
      "            684 COMPARE_OP               0 (<)\n",
      "            686 EXTENDED_ARG             2\n",
      "            688 POP_JUMP_IF_FALSE      694\n",
      "            690 LOAD_CONST               6 (1)\n",
      "            692 JUMP_FORWARD             2 (to 696)\n",
      "        >>  694 LOAD_CONST               7 (0)\n",
      "        >>  696 LOAD_CONST              58 (198398)\n",
      "            698 BUILD_LIST               2\n",
      "            700 CALL_METHOD              1\n",
      "            702 LOAD_CONST              59 (18956)\n",
      "            704 LOAD_NAME                3 (math)\n",
      "            706 LOAD_METHOD              4 (prod)\n",
      "            708 LOAD_CONST              60 (196905722)\n",
      "            710 LOAD_CONST              61 (112)\n",
      "            712 LOAD_CONST              61 (112)\n",
      "            714 COMPARE_OP               2 (==)\n",
      "            716 EXTENDED_ARG             2\n",
      "            718 POP_JUMP_IF_FALSE      724\n",
      "            720 LOAD_CONST               6 (1)\n",
      "            722 JUMP_FORWARD             2 (to 726)\n",
      "        >>  724 LOAD_CONST               7 (0)\n",
      "        >>  726 BUILD_LIST               2\n",
      "            728 CALL_METHOD              1\n",
      "            730 LOAD_NAME                0 (sum)\n",
      "            732 BUILD_LIST               0\n",
      "            734 LOAD_CONST              62 ((4217206544, 48993801750, 25736, 3879782983))\n",
      "            736 LIST_EXTEND              1\n",
      "            738 CALL_FUNCTION            1\n",
      "            740 LOAD_NAME                3 (math)\n",
      "            742 LOAD_METHOD              4 (prod)\n",
      "            744 LOAD_NAME                0 (sum)\n",
      "            746 BUILD_LIST               0\n",
      "            748 LOAD_CONST              63 ((2, 15, 4))\n",
      "            750 LIST_EXTEND              1\n",
      "            752 CALL_FUNCTION            1\n",
      "            754 LOAD_NAME                0 (sum)\n",
      "            756 BUILD_LIST               0\n",
      "            758 LOAD_CONST              64 ((4, 15, 11))\n",
      "            760 LIST_EXTEND              1\n",
      "            762 CALL_FUNCTION            1\n",
      "            764 LOAD_NAME                0 (sum)\n",
      "            766 BUILD_LIST               0\n",
      "            768 LOAD_CONST              65 ((7, 15, 9))\n",
      "            770 LIST_EXTEND              1\n",
      "            772 CALL_FUNCTION            1\n",
      "            774 BUILD_LIST               3\n",
      "            776 CALL_METHOD              1\n",
      "            778 LOAD_CONST              66 (211)\n",
      "            780 LOAD_NAME                3 (math)\n",
      "            782 LOAD_METHOD              4 (prod)\n",
      "            784 LOAD_CONST              67 (16)\n",
      "            786 LOAD_CONST              68 (63733)\n",
      "            788 COMPARE_OP               4 (>)\n",
      "            790 EXTENDED_ARG             3\n",
      "            792 POP_JUMP_IF_FALSE      798\n",
      "            794 LOAD_CONST               6 (1)\n",
      "            796 JUMP_FORWARD             2 (to 800)\n",
      "        >>  798 LOAD_CONST               7 (0)\n",
      "        >>  800 LOAD_CONST              69 (44586)\n",
      "            802 BUILD_LIST               2\n",
      "            804 CALL_METHOD              1\n",
      "            806 LOAD_NAME                0 (sum)\n",
      "            808 LOAD_CONST              70 (14)\n",
      "            810 LOAD_CONST               6 (1)\n",
      "            812 BUILD_LIST               2\n",
      "            814 CALL_FUNCTION            1\n",
      "            816 LOAD_NAME                2 (max)\n",
      "            818 LOAD_CONST              71 (3511)\n",
      "            820 LOAD_CONST              72 (10)\n",
      "            822 BUILD_LIST               2\n",
      "            824 CALL_FUNCTION            1\n",
      "            826 LOAD_NAME                2 (max)\n",
      "            828 BUILD_LIST               0\n",
      "            830 LOAD_CONST              73 ((12718799, 171629, 9, 264022477, 98))\n",
      "            832 LIST_EXTEND              1\n",
      "            834 CALL_FUNCTION            1\n",
      "            836 LOAD_NAME                3 (math)\n",
      "            838 LOAD_METHOD              4 (prod)\n",
      "            840 LOAD_CONST              74 (535767221581)\n",
      "            842 LOAD_NAME                0 (sum)\n",
      "            844 BUILD_LIST               0\n",
      "            846 LOAD_CONST              75 ((12, 10, 11))\n",
      "            848 LIST_EXTEND              1\n",
      "            850 CALL_FUNCTION            1\n",
      "            852 LOAD_NAME                0 (sum)\n",
      "            854 BUILD_LIST               0\n",
      "            856 LOAD_CONST              76 ((11, 2, 9))\n",
      "            858 LIST_EXTEND              1\n",
      "            860 CALL_FUNCTION            1\n",
      "            862 COMPARE_OP               0 (<)\n",
      "            864 EXTENDED_ARG             3\n",
      "            866 POP_JUMP_IF_FALSE      872\n",
      "            868 LOAD_CONST               6 (1)\n",
      "            870 JUMP_FORWARD             2 (to 874)\n",
      "        >>  872 LOAD_CONST               7 (0)\n",
      "        >>  874 BUILD_LIST               2\n",
      "            876 CALL_METHOD              1\n",
      "            878 LOAD_NAME                1 (min)\n",
      "            880 BUILD_LIST               0\n",
      "            882 LOAD_CONST              77 ((391364, 3067700, 611, 2388317100, 141))\n",
      "            884 LIST_EXTEND              1\n",
      "            886 CALL_FUNCTION            1\n",
      "            888 LOAD_NAME                3 (math)\n",
      "            890 LOAD_METHOD              4 (prod)\n",
      "            892 LOAD_CONST              78 (237)\n",
      "            894 LOAD_CONST              78 (237)\n",
      "            896 COMPARE_OP               0 (<)\n",
      "            898 EXTENDED_ARG             3\n",
      "            900 POP_JUMP_IF_FALSE      906\n",
      "            902 LOAD_CONST               6 (1)\n",
      "            904 JUMP_FORWARD             2 (to 908)\n",
      "        >>  906 LOAD_CONST               7 (0)\n",
      "        >>  908 LOAD_CONST              79 (3462)\n",
      "            910 BUILD_LIST               2\n",
      "            912 CALL_METHOD              1\n",
      "            914 LOAD_NAME                3 (math)\n",
      "            916 LOAD_METHOD              4 (prod)\n",
      "            918 BUILD_LIST               0\n",
      "            920 LOAD_CONST              80 ((139, 53, 151))\n",
      "            922 LIST_EXTEND              1\n",
      "            924 CALL_METHOD              1\n",
      "            926 LOAD_CONST              81 (7)\n",
      "            928 LOAD_NAME                0 (sum)\n",
      "            930 BUILD_LIST               0\n",
      "            932 LOAD_CONST              82 ((12998225, 689, 2007, 5, 826))\n",
      "            934 LIST_EXTEND              1\n",
      "            936 CALL_FUNCTION            1\n",
      "            938 LOAD_CONST              83 (547)\n",
      "            940 LOAD_NAME                3 (math)\n",
      "            942 LOAD_METHOD              4 (prod)\n",
      "            944 LOAD_CONST              84 (193)\n",
      "            946 LOAD_CONST              85 (1458)\n",
      "            948 LOAD_CONST              86 (138)\n",
      "            950 COMPARE_OP               0 (<)\n",
      "            952 EXTENDED_ARG             3\n",
      "            954 POP_JUMP_IF_FALSE      960\n",
      "            956 LOAD_CONST               6 (1)\n",
      "            958 JUMP_FORWARD             2 (to 962)\n",
      "        >>  960 LOAD_CONST               7 (0)\n",
      "        >>  962 BUILD_LIST               2\n",
      "            964 CALL_METHOD              1\n",
      "            966 LOAD_NAME                3 (math)\n",
      "            968 LOAD_METHOD              4 (prod)\n",
      "            970 LOAD_CONST              87 (277997)\n",
      "            972 LOAD_CONST              88 (12)\n",
      "            974 COMPARE_OP               2 (==)\n",
      "            976 EXTENDED_ARG             3\n",
      "            978 POP_JUMP_IF_FALSE      984\n",
      "            980 LOAD_CONST               6 (1)\n",
      "            982 JUMP_FORWARD             2 (to 986)\n",
      "        >>  984 LOAD_CONST               7 (0)\n",
      "        >>  986 LOAD_CONST              89 (37675211133)\n",
      "            988 BUILD_LIST               2\n",
      "            990 CALL_METHOD              1\n",
      "            992 LOAD_CONST              90 (11)\n",
      "            994 LOAD_NAME                3 (math)\n",
      "            996 LOAD_METHOD              4 (prod)\n",
      "            998 LOAD_CONST              91 (955)\n",
      "           1000 LOAD_CONST              92 (2610)\n",
      "           1002 COMPARE_OP               4 (>)\n",
      "           1004 EXTENDED_ARG             3\n",
      "           1006 POP_JUMP_IF_FALSE     1012\n",
      "           1008 LOAD_CONST               6 (1)\n",
      "           1010 JUMP_FORWARD             2 (to 1014)\n",
      "        >> 1012 LOAD_CONST               7 (0)\n",
      "        >> 1014 LOAD_CONST              93 (67374456587)\n",
      "           1016 BUILD_LIST               2\n",
      "           1018 CALL_METHOD              1\n",
      "           1020 LOAD_NAME                0 (sum)\n",
      "           1022 BUILD_LIST               0\n",
      "           1024 LOAD_CONST              94 ((886515, 86, 254))\n",
      "           1026 LIST_EXTEND              1\n",
      "           1028 CALL_FUNCTION            1\n",
      "           1030 LOAD_CONST              95 (3)\n",
      "           1032 BUILD_LIST              53\n",
      "           1034 CALL_FUNCTION            1\n",
      "           1036 RETURN_VALUE\n"
     ]
    }
   ],
   "source": [
    "import dis\n",
    "dis.dis(ast.unparse(ast.fix_missing_locations(module)))"
   ]
  },
  {
   "cell_type": "code",
   "execution_count": null,
   "metadata": {},
   "outputs": [],
   "source": []
  }
 ],
 "metadata": {
  "interpreter": {
   "hash": "9bf743333e41296147f6a175b2ffd0bcec11fd937fe5651b295727fd77246a74"
  },
  "kernelspec": {
   "display_name": "Python 3.9.2 64-bit",
   "language": "python",
   "name": "python3"
  },
  "language_info": {
   "codemirror_mode": {
    "name": "ipython",
    "version": 3
   },
   "file_extension": ".py",
   "mimetype": "text/x-python",
   "name": "python",
   "nbconvert_exporter": "python",
   "pygments_lexer": "ipython3",
   "version": "3.9.7"
  },
  "orig_nbformat": 4
 },
 "nbformat": 4,
 "nbformat_minor": 2
}
